asphalt/influxdb/__init__.py
asphalt/influxdb/client.py
asphalt/influxdb/component.py
asphalt/influxdb/query.py
asphalt/influxdb/utils.py
asphalt_influxdb-2.1.0.dist-info/DESCRIPTION.rst
asphalt_influxdb-2.1.0.dist-info/METADATA
asphalt_influxdb-2.1.0.dist-info/RECORD
asphalt_influxdb-2.1.0.dist-info/WHEEL
asphalt_influxdb-2.1.0.dist-info/entry_points.txt
asphalt_influxdb-2.1.0.dist-info/metadata.json
asphalt_influxdb-2.1.0.dist-info/top_level.txt
