Metadata-Version: 2.0
Name: asphalt-influxdb
Version: 2.1.0
Summary: InfluxDB client component for the Asphalt framework
Home-page: https://github.com/asphalt-framework/asphalt-influxdb
Author: Alex Grönholm
Author-email: alex.gronholm@nextday.fi
License: Apache License 2.0
Platform: UNKNOWN
Classifier: Development Status :: 5 - Production/Stable
Classifier: Intended Audience :: Developers
Classifier: License :: OSI Approved :: Apache Software License
Classifier: Topic :: Database
Classifier: Programming Language :: Python
Classifier: Programming Language :: Python :: 3
Classifier: Programming Language :: Python :: 3.5
Classifier: Programming Language :: Python :: 3.6
Requires-Dist: aiohttp (~=2.0)
Requires-Dist: asphalt (>=3.0,<5.0)
Requires-Dist: python-dateutil (~=2.6)
Requires-Dist: typeguard (~=2.0)
Provides-Extra: testing
Requires-Dist: pytest; extra == 'testing'
Requires-Dist: pytest-asyncio (>=0.5.0); extra == 'testing'
Requires-Dist: pytest-catchlog; extra == 'testing'
Requires-Dist: pytest-cov; extra == 'testing'
